Workbook

Sheet INCOME STATEMENT-TREND ANALYSIS
A1: HEROMOTOCORP LTD
A2: INCOME STATEMENT
A3: INR ( CR )
A4: PARTICULAR | C4: 41729 | D4: 42094 | E4: 42460 | F4: 42825 | G4: 43190 | H4: 43555
A5: Revenue from operations | C5: ='income statement'!C5/'income statement'!C$5 -> 1 | D5: ='income statement'!D5/'income statement'!D$5 -> 1 | E5: ='income statement'!E5/'income statement'!E$5 -> 1 | F5: ='income statement'!F5/'income statement'!F$5 -> 1 | G5: ='income statement'!G5/'income statement'!G$5 -> 1 | H5: ='income statement'!H5/'income statement'!H$5 -> 1 | I5: operating item
A6: operating expenses
A7: cost of materials consumed | C7: =-'income statement'!C7/'income statement'!C$5 -> 0.67506017 | D7: =-'income statement'!D7/'income statement'!D$5 -> 0.67933565 | E7: =-'income statement'!E7/'income statement'!E$5 -> 0.62861794 | F7: =-'income statement'!F7/'income statement'!F$5 -> 0.61696359 | G7: =-'income statement'!G7/'income statement'!G$5 -> 0.66058427 | H7: =-'income statement'!H7/'income statement'!H$5 -> 0.69009773 | I7: operating item
A8: excise duty on sale of goods | C8: =-'income statement'!C8/'income statement'!C$5 -> 0.069616738 | D8: =-'income statement'!D8/'income statement'!D$5 -> 0.059198511 | E8: =-'income statement'!E8/'income statement'!E$5 -> 0.073514569 | F8: =-'income statement'!F8/'income statement'!F$5 -> 0.076587916 | G8: =-'income statement'!G8/'income statement'!G$5 -> 0.019425395 | H8: =-'income statement'!H8/'income statement'!H$5 -> 2.9436006e-05 | I8: operating item
A9: employee benefits expenses | C9: =-'income statement'!C9/'income statement'!C$5 -> 0.034438067 | D9: =-'income statement'!D9/'income statement'!D$5 -> 0.040625754 | E9: =-'income statement'!E9/'income statement'!E$5 -> 0.043594335 | F9: =-'income statement'!F9/'income statement'!F$5 -> 0.046217403 | G9: =-'income statement'!G9/'income statement'!G$5 -> 0.047853539 | H9: =-'income statement'!H9/'income statement'!H$5 -> 0.052337219 | I9: operating item
A10: other expenses | C10: =-'income statement'!C10/'income statement'!C$5 -> 0.089835216 | D10: =-'income statement'!D10/'income statement'!D$5 -> 0.10037559 | E10: =-'income statement'!E10/'income statement'!E$5 -> 0.11108579 | F10: =-'income statement'!F10/'income statement'!F$5 -> 0.11250968 | G10: =-'income statement'!G10/'income statement'!G$5 -> 0.11069152 | H10: =-'income statement'!H10/'income statement'!H$5 -> 0.1097963 | I10: operating item
A11: Total operating expenses | C11: =-'income statement'!C11/'income statement'!C$5 -> -0.86895019 | D11: =-'income statement'!D11/'income statement'!D$5 -> -0.87950105 | E11: =-'income statement'!E11/'income statement'!E$5 -> -0.85684519 | F11: =-'income statement'!F11/'income statement'!F$5 -> -0.85231087 | G11: =-'income statement'!G11/'income statement'!G$5 -> -0.83912873 | H11: =-'income statement'!H11/'income statement'!H$5 -> -0.85229012
A12: EBITDA | C12: =C5+C11 -> 0.13104981 | D12: =D5+D11 -> 0.12049895 | E12: =E5+E11 -> 0.14315481 | F12: =F5+F11 -> 0.14768913 | G12: =G5+G11 -> 0.16087127 | H12: =H5+H11 -> 0.14770988
A13: Depreciation and amortisation expenses | C13: ='income statement'!C13/'income statement'!C$5 -> -0.040992409 | D13: ='income statement'!D13/'income statement'!D$5 -> -0.018607215 | E13: ='income statement'!E13/'income statement'!E$5 -> -0.01442292 | F13: =-'income statement'!F13/'income statement'!F$5 -> -0.016201911 | G13: ='income statement'!G13/'income statement'!G$5 -> -0.017371076 | H13: ='income statement'!H13/'income statement'!H$5 -> -0.018368068 | I13: operating item
A14: EBIT | C14: ='income statement'!C14/'income statement'!C$5 -> 0.090057397 | D14: ='income statement'!D14/'income statement'!D$5 -> 0.10189173 | E14: ='income statement'!E14/'income statement'!E$5 -> 0.12873189 | F14: =-'income statement'!F14/'income statement'!F$5 -> -0.13148722 | G14: ='income statement'!G14/'income statement'!G$5 -> 0.1435002 | H14: ='income statement'!H14/'income statement'!H$5 -> 0.12934181
A15: Other income | C15: ='income statement'!C15/'income statement'!C$5 -> 0.0164414 | D15: ='income statement'!D15/'income statement'!D$5 -> 0.011956859 | E15: ='income statement'!E15/'income statement'!E$5 -> 0.013446199 | F15: =-'income statement'!F15/'income statement'!F$5 -> -0.016847405 | G15: ='income statement'!G15/'income statement'!G$5 -> 0.015800127 | H15: ='income statement'!H15/'income statement'!H$5 -> 0.020222536 | I15: non-operating item
A16: Finance cost | C16: ='income statement'!C16/'income statement'!C$5 -> -0.00044436216 | D16: ='income statement'!D16/'income statement'!D$5 -> -0.00041349368 | E16: ='income statement'!E16/'income statement'!E$5 -> -0.00048836074 | F16: =-'income statement'!F16/'income statement'!F$5 -> 0.00087141751 | G16: ='income statement'!G16/'income statement'!G$5 -> -0.0009365276 | H16: ='income statement'!H16/'income statement'!H$5 -> -0.0010891322 | I16: non-operating item
A17: share in profit/(loss) of associate , net of tax | C17: ='income statement'!C17/'income statement'!C$5 -> -0.00014812072 | D17: ='income statement'!D17/'income statement'!D$5 -> 0.0005168671 | E17: ='income statement'!E17/'income statement'!E$5 -> 0.001106951 | F17: =-'income statement'!F17/'income statement'!F$5 -> -0.0017751097 | G17: ='income statement'!G17/'income statement'!G$5 -> 0.0015105284 | H17: ='income statement'!H17/'income statement'!H$5 -> 0.0017955964 | I17: non-operating item
A18: Gain on dilution of interest in an associate | C18: ='income statement'!C18/'income statement'!C$5 -> 0 | D18: ='income statement'!D18/'income statement'!D$5 -> 0 | E18: ='income statement'!E18/'income statement'!E$5 -> 0 | F18: =-'income statement'!F18/'income statement'!F$5 -> -0.0084559773 | G18: 0 | H18: 0 | I18: non-operating item
A19: minority interest profit / ( loss ) | C19: ='income statement'!C19/'income statement'!C$5 -> 0 | D19: ='income statement'!D19/'income statement'!D$5 -> 3.4457806e-05 | E19: ='income statement'!E19/'income statement'!E$5 -> 0.00013022953 | F19: =-'income statement'!F19/'income statement'!F$5 -> 0 | G19: ='income statement'!G19/'income statement'!G$5 -> 0 | H19: 0
A20: profit before tax | C20: ='income statement'!C20/'income statement'!C$5 -> 0.10590631 | D20: ='income statement'!D20/'income statement'!D$5 -> 0.11398642 | E20: ='income statement'!E20/'income statement'!E$5 -> 0.14292691 | F20: =-'income statement'!F20/'income statement'!F$5 -> -0.15769429 | G20: ='income statement'!G20/'income statement'!G$5 -> 0.15987432 | H20: ='income statement'!H20/'income statement'!H$5 -> 0.15027081
A21: Tax expenses | C21: ='income statement'!C21/'income statement'!C$5 -> -0.028068876 | D21: ='income statement'!D21/'income statement'!D$5 -> -0.032493711 | E21: ='income statement'!E21/'income statement'!E$5 -> -0.041510663 | F21: ='income statement'!F21/'income statement'!F$5 -> -0.043215853 | G21: ='income statement'!G21/'income statement'!G$5 -> -0.047430591 | H21: ='income statement'!H21/'income statement'!H$5 -> -0.048216178 | I21: operating item
A22: Profit after tax / Net profit | C22: ='income statement'!C22/'income statement'!C$5 -> 0.077837438 | D22: ='income statement'!D22/'income statement'!D$5 -> 0.081492712 | E22: ='income statement'!E22/'income statement'!E$5 -> 0.10141625 | F22: ='income statement'!G22/'income statement'!G$5 -> 0.11244373 | G22: ='income statement'!G22/'income statement'!G$5 -> 0.11244373 | H22: ='income statement'!H22/'income statement'!H$5 -> 0.10205463

Sheet income statement
A1: HEROMOTOCORP LTD
A2: INCOME STATEMENT
A3: INR ( CR )
A4: PARTICULAR | C4: 41729 | D4: 42094 | E4: 42460 | F4: 42825 | G4: 43190 | H4: 43555
A5: Revenue from operations | C5: 27005 | D5: 29021 | E5: 30715 | F5: 30984 | G5: 33101 | H5: 33972 | J5: operating item
A6: operating expenses
A7: cost of materials consumed | C7: -18230 | D7: -19715 | E7: -19308 | F7: -19116 | G7: -21866 | H7: -23444 | J7: operating item
A8: excise duty on sale of goods | C8: -1880 | D8: -1718 | E8: -2258 | F8: -2373 | G8: -643 | H8: -1 | J8: operating item
A9: employee benefits expenses | C9: -930 | D9: -1179 | E9: -1339 | F9: -1432 | G9: -1584 | H9: -1778 | J9: operating item
A10: other expenses | C10: -2426 | D10: -2913 | E10: -3412 | F10: -3486 | G10: -3664 | H10: -3730 | J10: operating item
A11: Total operating expenses | C11: 23466 | D11: 25524 | E11: 26318 | F11: 26408 | G11: 27776 | H11: 28954
A12: EBITDA | C12: =C5-C11 -> 3539 | D12: =D5-D11 -> 3497 | E12: =E5-E11 -> 4397 | F12: =F5-F11 -> 4576 | G12: =G5-G11 -> 5325 | H12: =H5-H11 -> 5018
A13: Depreciation and amortisation expenses | C13: -1107 | D13: -540 | E13: -443 | F13: 502 | G13: -575 | H13: -624 | J13: operating item
A14: EBIT | C14: =SUM(C12:C13) -> 2432 | D14: =SUM(D12:D13) -> 2957 | E14: =SUM(E12:E13) -> 3954 | F14: =F12-F13 -> 4074 | G14: =SUM(G12:G13) -> 4750 | H14: =SUM(H12:H13) -> 4394
A15: Other income | C15: 444 | D15: 347 | E15: 413 | F15: 522 | G15: 523 | H15: 687 | J15: non-operating item
A16: Finance cost | C16: -12 | D16: -12 | E16: -15 | F16: -27 | G16: -31 | H16: -37 | J16: non-operating item
A17: share in profit/(loss) of associate , net of tax | C17: -4 | D17: 15 | E17: 34 | F17: 55 | G17: 50 | H17: 61 | J17: non-operating item
A18: Gain on dilution of interest in an associate | F18: 262 | G18: - | H18: - | J18: non-operating item
A19: minority interest profit / ( loss ) | C19: 0 | D19: 1 | E19: 4 | H19: -
A20: profit before tax | C20: =SUM(C14:C19) -> 2860 | D20: =SUM(D14:D19) -> 3308 | E20: =SUM(E14:E19) -> 4390 | F20: =SUM(F14:F18) -> 4886 | G20: =SUM(G14:G17) -> 5292 | H20: =SUM(H14:H17) -> 5105
A21: Tax expenses | C21: -758 | D21: -943 | E21: -1275 | F21: -1339 | G21: -1570 | H21: -1638 | J21: operating item
A22: Profit after tax / Net profit | C22: =SUM(C20:C21) -> 2102 | D22: =SUM(D20:D21) -> 2365 | E22: =SUM(E20:E21) -> 3115 | F22: =SUM(F20:F21) -> 3547 | G22: =SUM(G20:G21) -> 3722 | H22: =SUM(H20:H21) -> 3467

Sheet balance sheet trend analysis
A1: HEROMOTOCORP LTD
A2: BALANCE SHEET
A3: INR ( CR )
A5: PARTICULAR | C5: 41729 | D5: 42094 | E5: 42460 | F5: 42825 | G5: 43190 | H5: 43555
A6: ASSETS
A7: NON - CURRENT ASSET
A8: property , plant and equipment | C8: ='balance sheet'!C8/'balance sheet'!C$32 -> 0.18741355 | D8: ='balance sheet'!D8/'balance sheet'!D$32 -> 0.26759902 | E8: ='balance sheet'!E8/'balance sheet'!E$32 -> 0.30831755 | F8: ='balance sheet'!F8/'balance sheet'!F$32 -> 0.29355869 | G8: ='balance sheet'!G8/'balance sheet'!G$32 -> 0.27426725 | H8: ='balance sheet'!H8/'balance sheet'!H$32 -> 0.25899106 | I8: Operating item
A9: capital work in progress | C9: ='balance sheet'!C9/'balance sheet'!C$32 -> 0.084469472 | D9: ='balance sheet'!D9/'balance sheet'!D$32 -> 0.02956636 | E9: ='balance sheet'!E9/'balance sheet'!E$32 -> 0.026120581 | F9: ='balance sheet'!F9/'balance sheet'!F$32 -> 0.025241476 | G9: ='balance sheet'!G9/'balance sheet'!G$32 -> 0.01373808 | H9: ='balance sheet'!H9/'balance sheet'!H$32 -> 0.020800346 | I9: Operating item
A10: intangible asset | C10: ='balance sheet'!C10/'balance sheet'!C$32 -> 0.034578147 | D10: ='balance sheet'!D10/'balance sheet'!D$32 -> 0.0094800075 | E10: ='balance sheet'!E10/'balance sheet'!E$32 -> 0.010179924 | F10: ='balance sheet'!F10/'balance sheet'!F$32 -> 0.0067789526 | G10: ='balance sheet'!G10/'balance sheet'!G$32 -> 0.010898493 | H10: ='balance sheet'!H10/'balance sheet'!H$32 -> 0.0086411413 | I10: Operating item
A11: intangible asset under devolopment | C11: 0 | D11: ='balance sheet'!D11/'balance sheet'!D$32 -> 0.03792003 | E11: ='balance sheet'!E11/'balance sheet'!E$32 -> 0.025489268 | F11: ='balance sheet'!F11/'balance sheet'!F$32 -> 0.012702373 | G11: ='balance sheet'!G11/'balance sheet'!G$32 -> 0.0066965954 | H11: ='balance sheet'!H11/'balance sheet'!H$32 -> 0.010159691 | I11: Operating item
A12: equity accounted investments in associates | C12: 0 | D12: ='balance sheet'!D12/'balance sheet'!D$32 -> 0.066453914 | E12: ='balance sheet'!E12/'balance sheet'!E$32 -> 0.074968434 | F12: ='balance sheet'!F12/'balance sheet'!F$32 -> 0.066966647 | G12: ='balance sheet'!G12/'balance sheet'!G$32 -> 0.066655554 | H12: ='balance sheet'!H12/'balance sheet'!H$32 -> 0.092188387 | I12: non-operating item
A13: investments | C13: ='balance sheet'!C13/'balance sheet'!C$32 -> 0.086741751 | D13: ='balance sheet'!D13/'balance sheet'!D$32 -> 0.077060259 | E13: ='balance sheet'!E13/'balance sheet'!E$32 -> 0.074573864 | F13: ='balance sheet'!F13/'balance sheet'!F$32 -> 0.03245146 | G13: ='balance sheet'!G13/'balance sheet'!G$32 -> 0.052796763 | H13: ='balance sheet'!H13/'balance sheet'!H$32 -> 0.066691886 | I13: non-operating item
A14: loans to employee | C14: ='balance sheet'!C14/'balance sheet'!C$32 -> 0.047125074 | D14: 0 | E14: 0 | F14: ='balance sheet'!F14/'balance sheet'!F$32 -> 0.0015086108 | G14: ='balance sheet'!G14/'balance sheet'!G$32 -> 0.0012818376 | H14: ='balance sheet'!H14/'balance sheet'!H$32 -> 0.0032478586 | I14: non-operating item
A15: security deposits | C15: 0 | D15: 0 | E15: 0 | F15: ='balance sheet'!F15/'balance sheet'!F$32 -> 0.0016588188 | G15: ='balance sheet'!G15/'balance sheet'!G$32 -> 0.0013565635 | H15: ='balance sheet'!H15/'balance sheet'!H$32 -> 0.0018265827 | I15: Operating item
A16: deferred tax assets ( net ) | C16: ='balance sheet'!C16/'balance sheet'!C$32 -> 0.010472239 | D16: ='balance sheet'!D16/'balance sheet'!D$32 -> 0.0069457481 | E16: 0 | F16: ='balance sheet'!F16/'balance sheet'!F$32 -> 0 | G16: ='balance sheet'!G16/'balance sheet'!G$32 -> 0 | H16: 0 | I16: non-operating item
A17: income tax assets (net) | C17: 0 | D17: 0 | E17: 0 | F17: ='balance sheet'!F17/'balance sheet'!F$32 -> 0.021714853 | G17: ='balance sheet'!G17/'balance sheet'!G$32 -> 0.022676454 | H17: ='balance sheet'!H17/'balance sheet'!H$32 -> 0.046237402 | I17: Operating item
A18: other non-current assets | C18: 0 | D18: 0 | E18: 0 | F18: ='balance sheet'!F18/'balance sheet'!F$32 -> 0.042998674 | G18: ='balance sheet'!G18/'balance sheet'!G$32 -> 0.03216665 | H18: ='balance sheet'!H18/'balance sheet'!H$32 -> 0.036558675 | I18: Operating item
A19: TOTAL NON-CUURENT ASSET | C19: ='balance sheet'!C19/'balance sheet'!C$32 -> 0.45080024 | D19: ='balance sheet'!D19/'balance sheet'!D$32 -> 0.49502534 | E19: ='balance sheet'!E19/'balance sheet'!E$32 -> 0.51964962 | F19: ='balance sheet'!F19/'balance sheet'!F$32 -> 0.50558055 | G19: ='balance sheet'!G19/'balance sheet'!G$32 -> 0.48253424 | H19: ='balance sheet'!H19/'balance sheet'!H$32 -> 0.54534302
A21: CURRENT ASSET
A22: inventories | C22: ='balance sheet'!C22/'balance sheet'!C$32 -> 0.066192452 | D22: ='balance sheet'!D22/'balance sheet'!D$32 -> 0.080814717 | E22: ='balance sheet'!E22/'balance sheet'!E$32 -> 0.060132576 | F22: ='balance sheet'!F22/'balance sheet'!F$32 -> 0.046277127 | G22: ='balance sheet'!G22/'balance sheet'!G$32 -> 0.055337445 | H22: ='balance sheet'!H22/'balance sheet'!H$32 -> 0.067524116 | I22: Operating item
A23: investments | C23: ='balance sheet'!C23/'balance sheet'!$C$32 -> 0.32365145 | D23: ='balance sheet'!D23/'balance sheet'!D$32 -> 0.21559977 | E23: ='balance sheet'!E23/'balance sheet'!E$32 -> 0.25639205 | F23: ='balance sheet'!F23/'balance sheet'!F$32 -> 0.2967653 | G23: ='balance sheet'!G23/'balance sheet'!G$32 -> 0.32138484 | H23: ='balance sheet'!H23/'balance sheet'!H$32 -> 0.17152044 | I23: non - current item
A24: trade receivables | C24: ='balance sheet'!C24/'balance sheet'!$C$32 -> 0.090989923 | D24: ='balance sheet'!D24/'balance sheet'!D$32 -> 0.12877792 | E24: ='balance sheet'!E24/'balance sheet'!E$32 -> 0.10116793 | F24: ='balance sheet'!F24/'balance sheet'!F$32 -> 0.10134469 | G24: ='balance sheet'!G24/'balance sheet'!G$32 -> 0.082026108 | H24: ='balance sheet'!H24/'balance sheet'!H$32 -> 0.1483477 | I24: Operating item
A25: cash and cash equivalents | C25: ='balance sheet'!C25/'balance sheet'!$C$32 -> 0.011855365 | D25: ='balance sheet'!D25/'balance sheet'!D$32 -> 0.020274075 | E25: ='balance sheet'!E25/'balance sheet'!E$32 -> 0.014125631 | F25: ='balance sheet'!F25/'balance sheet'!F$32 -> 0.0048393101 | G25: ='balance sheet'!G25/'balance sheet'!G$32 -> 0.0075070846 | H25: ='balance sheet'!H25/'balance sheet'!H$32 -> 0.011245913 | I25: Operating item
A26: bank balances | C26: 0 | D26: 0 | E26: 0 | F26: ='balance sheet'!F26/'balance sheet'!F$32 -> 0.0079218396 | G26: ='balance sheet'!G26/'balance sheet'!G$32 -> 0.0061505211 | H26: ='balance sheet'!H26/'balance sheet'!H$32 -> 0.0051771191 | I26: Operating item
A27: loans to employees | C27: ='balance sheet'!C27/'balance sheet'!$C$32 -> 0.0017783047 | D27: ='balance sheet'!D27/'balance sheet'!D$32 -> 0.0022526751 | E27: ='balance sheet'!E27/'balance sheet'!E$32 -> 0.0018939394 | F27: ='balance sheet'!F27/'balance sheet'!F$32 -> 0.0014171799 | G27: ='balance sheet'!G27/'balance sheet'!G$32 -> 0.0012301042 | H27: ='balance sheet'!H27/'balance sheet'!H$32 -> 0.0012537491 | I27: non - current item
A28: security deposits | C28: ='balance sheet'!C28/'balance sheet'!$C$32 -> 9.8794705e-05 | D28: 0 | E28: 0 | F28: ='balance sheet'!F28/'balance sheet'!F$32 -> 0.00020898505 | G28: ='balance sheet'!G28/'balance sheet'!G$32 -> 0.00040811869 | H28: ='balance sheet'!H28/'balance sheet'!H$32 -> 0.00010267773 | I28: Operating item
A29: other financial asset | C29: ='balance sheet'!C29/'balance sheet'!$C$32 -> 0.0021734835 | D29: ='balance sheet'!D29/'balance sheet'!D$32 -> 0.0056316876 | E29: ='balance sheet'!E29/'balance sheet'!E$32 -> 0.0062342172 | F29: ='balance sheet'!F29/'balance sheet'!F$32 -> 0.0094696351 | G29: ='balance sheet'!G29/'balance sheet'!G$32 -> 0.031229702 | H29: ='balance sheet'!H29/'balance sheet'!H$32 -> 0.035353563 | I29: Operating item
A30: other cuurent asset | C30: ='balance sheet'!C30/'balance sheet'!$C$32 -> 0.052459988 | D30: ='balance sheet'!D30/'balance sheet'!D$32 -> 0.051623803 | E30: ='balance sheet'!E30/'balance sheet'!E$32 -> 0.04040404 | F30: ='balance sheet'!F30/'balance sheet'!F$32 -> 0.026175378 | G30: ='balance sheet'!G30/'balance sheet'!G$32 -> 0.012191827 | H30: ='balance sheet'!H30/'balance sheet'!H$32 -> 0.014131698 | I30: Operating item
A31: Total current asset | C31: ='balance sheet'!C31/'balance sheet'!C$32 -> 0.54919976 | D31: ='balance sheet'!D31/'balance sheet'!D$32 -> 0.50497466 | E31: ='balance sheet'!E31/'balance sheet'!E$32 -> 0.48035038 | F31: ='balance sheet'!F31/'balance sheet'!F$32 -> 0.49441945 | G31: ='balance sheet'!G31/'balance sheet'!G$32 -> 0.51746576 | H31: ='balance sheet'!H31/'balance sheet'!H$32 -> 0.45465698
A32: TOTAL ASSETS | C32: ='balance sheet'!C32/'balance sheet'!C$32 -> 1 | D32: ='balance sheet'!D32/'balance sheet'!D$32 -> 1 | E32: ='balance sheet'!E32/'balance sheet'!E$32 -> 1 | F32: ='balance sheet'!F32/'balance sheet'!F$32 -> 1 | G32: ='balance sheet'!G32/'balance sheet'!G$32 -> 1 | H32: ='balance sheet'!H32/'balance sheet'!H$32 -> 1
A34: PARTICULARS | C34: 41729 | D34: 42094 | E34: 42460 | F34: 42825 | G34: 43190 | H34: 43555
A35: LIABILITIES
A36: NON-CURRENT LIABILITIES
A37: Equity share capital | C37: ='balance sheet'!C37/'balance sheet'!C$56 -> 0.0039419087 | D37: ='balance sheet'!D37/'balance sheet'!D$56 -> 0.0037449668 | E37: ='balance sheet'!E37/'balance sheet'!E$56 -> 0.0031486742 | F37: ='balance sheet'!F37/'balance sheet'!F$56 -> 0.0026057824 | G37: ='balance sheet'!G37/'balance sheet'!G$56 -> 0.0022935121 | H37: ='balance sheet'!H37/'balance sheet'!H$56 -> 0.002161648 | I37: non - current item
A38: other equity | C38: ='balance sheet'!C38/'balance sheet'!C$56 -> 0.5515412 | D38: ='balance sheet'!D38/'balance sheet'!D$56 -> 0.6100917 | E38: ='balance sheet'!E38/'balance sheet'!E$56 -> 0.62442393 | F38: ='balance sheet'!F38/'balance sheet'!F$56 -> 0.67107712 | G38: ='balance sheet'!G38/'balance sheet'!G$56 -> 0.68584058 | H38: ='balance sheet'!H38/'balance sheet'!H$56 -> 0.70688593 | I38: non - current item
A39: non-controlling interest | C39: ='balance sheet'!C39/'balance sheet'!C$56 -> 8.8915234e-05 | D39: ='balance sheet'!D39/'balance sheet'!D$56 -> 0.0017363881 | E39: ='balance sheet'!E39/'balance sheet'!E$56 -> 0.004229798 | F39: ='balance sheet'!F39/'balance sheet'!F$56 -> 0.0044017476 | G39: ='balance sheet'!G39/'balance sheet'!G$56 -> 0.0053572763 | H39: ='balance sheet'!H39/'balance sheet'!H$56 -> 0.0062741834 | I39: non - current item
A40: LT debt | C40: 0 | D40: ='balance sheet'!D40/'balance sheet'!D$56 -> 0.0011263058 | E40: ='balance sheet'!E40/'balance sheet'!E$56 -> 0.011521465 | F40: ='balance sheet'!F40/'balance sheet'!F$56 -> 0.013577498 | G40: ='balance sheet'!G40/'balance sheet'!G$56 -> 0.0085992332 | H40: ='balance sheet'!H40/'balance sheet'!H$56 -> 0.0067443419 | I40: non - current item
A41: employee benefits | C41: ='balance sheet'!C41/'balance sheet'!C$56 -> 0.00085951393 | D41: ='balance sheet'!D41/'balance sheet'!D$56 -> 0.00095735994 | E41: ='balance sheet'!E41/'balance sheet'!E$56 -> 0.001238952 | F41: ='balance sheet'!F41/'balance sheet'!F$56 -> 0.0010579868 | G41: ='balance sheet'!G41/'balance sheet'!G$56 -> 0.001488771 | H41: ='balance sheet'!H41/'balance sheet'!H$56 -> 0.0015347701 | I41: non - current item
A42: other long term liabilities | C42: ='balance sheet'!C42/'balance sheet'!C$56 -> 0.0024204703 | D42: ='balance sheet'!D42/'balance sheet'!D$56 -> 0.002937781 | E42: ='balance sheet'!E42/'balance sheet'!E$56 -> 0.0027541035 | F42: 0 | G42: 0 | H42: 0 | I42: Operating item
A43: warrenties | C43: ='balance sheet'!C43/'balance sheet'!C$56 -> 0.0040901008 | D43: ='balance sheet'!D43/'balance sheet'!D$56 -> 0.0052654797 | E43: ='balance sheet'!E43/'balance sheet'!E$56 -> 0.0054450758 | F43: ='balance sheet'!F43/'balance sheet'!F$56 -> 0.0038858158 | G43: ='balance sheet'!G43/'balance sheet'!G$56 -> 0.0053572763 | H43: ='balance sheet'!H43/'balance sheet'!H$56 -> 0.0049988111 | I43: Operating item
A44: deferred tax liabilities ( net ) | C44: 0 | D44: 0 | E44: ='balance sheet'!E44/'balance sheet'!E$56 -> 0.017976641 | F44: ='balance sheet'!F44/'balance sheet'!F$56 -> 0.030622841 | G44: ='balance sheet'!G44/'balance sheet'!G$56 -> 0.033448488 | H44: ='balance sheet'!H44/'balance sheet'!H$56 -> 0.033121852 | I44: non - current item
A45: Total non -cuurent liabilities | C45: ='balance sheet'!C45/'balance sheet'!C$56 -> 0.56294211 | D45: ='balance sheet'!D45/'balance sheet'!D$56 -> 0.62585998 | E45: ='balance sheet'!E45/'balance sheet'!E$56 -> 0.67073864 | F45: ='balance sheet'!F45/'balance sheet'!F$56 -> 0.72722879 | G45: ='balance sheet'!G45/'balance sheet'!G$56 -> 0.74238514 | H45: ='balance sheet'!H45/'balance sheet'!H$56 -> 0.76172154
A47: CURRENT LIABILITIES
A48: ST debt | C48: 0 | D48: ='balance sheet'!D48/'balance sheet'!D$56 -> 0.0082595759 | E48: ='balance sheet'!E48/'balance sheet'!E$56 -> 0.0066366793 | F48: ='balance sheet'!F48/'balance sheet'!F$56 -> 0.0026188439 | G48: ='balance sheet'!G48/'balance sheet'!G$56 -> 0.0043341055 | H48: ='balance sheet'!H48/'balance sheet'!H$56 -> 0.0099273686 | I48: non - current item
A49: trade payables | C49: ='balance sheet'!C49/'balance sheet'!C$56 -> 0.22633867 | D49: ='balance sheet'!D49/'balance sheet'!D$56 -> 0.25464836 | E49: ='balance sheet'!E49/'balance sheet'!E$56 -> 0.22030461 | F49: ='balance sheet'!F49/'balance sheet'!F$56 -> 0.21330843 | G49: ='balance sheet'!G49/'balance sheet'!G$56 -> 0.19401732 | H49: ='balance sheet'!H49/'balance sheet'!H$56 -> 0.18580446 | I49: Operating item
A50: other financial liabilities | C50: ='balance sheet'!C50/'balance sheet'!C$56 -> 0.053388658 | D50: ='balance sheet'!D50/'balance sheet'!D$56 -> 0.037459054 | E50: ='balance sheet'!E50/'balance sheet'!E$56 -> 0.034951073 | F50: ='balance sheet'!F50/'balance sheet'!F$56 -> 0.020160527 | G50: ='balance sheet'!G50/'balance sheet'!G$56 -> 0.0084900183 | H50: ='balance sheet'!H50/'balance sheet'!H$56 -> 0.0090248806 | I50: non - current item
A51: security deposits dealers and others | C51: ='balance sheet'!C51/'balance sheet'!C$56 -> 0.0047223869 | D51: ='balance sheet'!D51/'balance sheet'!D$56 -> 0.004843115 | E51: ='balance sheet'!E51/'balance sheet'!E$56 -> 0.0043087121 | F51: ='balance sheet'!F51/'balance sheet'!F$56 -> 0.0040817393 | G51: ='balance sheet'!G51/'balance sheet'!G$56 -> 0.0033166829 | H51: ='balance sheet'!H51/'balance sheet'!H$56 -> 0.0032316638 | I51: Operating item
A52: other curent liabilities | C52: ='balance sheet'!C52/'balance sheet'!C$56 -> 0.15157084 | D52: ='balance sheet'!D52/'balance sheet'!D$56 -> 0.067690979 | E52: ='balance sheet'!E52/'balance sheet'!E$56 -> 0.060692866 | F52: ='balance sheet'!F52/'balance sheet'!F$56 -> 0.029819554 | G52: ='balance sheet'!G52/'balance sheet'!G$56 -> 0.043973352 | H52: ='balance sheet'!H52/'balance sheet'!H$56 -> 0.027063833 | I52: Operating item
A53: employee benefits | C53: ='balance sheet'!C53/'balance sheet'!C$56 -> 0.00028650464 | D53: ='balance sheet'!D53/'balance sheet'!D$56 -> 0.00027219057 | E53: ='balance sheet'!E53/'balance sheet'!E$56 -> 0.00029198232 | F53: ='balance sheet'!F53/'balance sheet'!F$56 -> 0.00033306993 | G53: ='balance sheet'!G53/'balance sheet'!G$56 -> 0.00032764458 | H53: ='balance sheet'!H53/'balance sheet'!H$56 -> 0.00031343897 | I53: non - current item
A54: warranties | C54: ='balance sheet'!C54/'balance sheet'!C$56 -> 0.00075083975 | D54: ='balance sheet'!D54/'balance sheet'!D$56 -> 0.00096674582 | E54: ='balance sheet'!E54/'balance sheet'!E$56 -> 0.0020754419 | F54: ='balance sheet'!F54/'balance sheet'!F$56 -> 0.0024490436 | G54: ='balance sheet'!G54/'balance sheet'!G$56 -> 0.0031557346 | H54: ='balance sheet'!H54/'balance sheet'!H$56 -> 0.0029128207 | I54: Operating item
A55: Total current liabilities | C55: =SUM(C48:C54) -> 0.43705789 | D55: =SUM(D48:D54) -> 0.37414002 | E55: =SUM(E48:E54) -> 0.32926136 | F55: =SUM(F48:F54) -> 0.27277121 | G55: =SUM(G48:G54) -> 0.25761486 | H55: =SUM(H48:H54) -> 0.23827846
A56: Total liabilities | C56: =C45+C55 -> 1 | D56: =D45+D55 -> 1 | E56: =E45+E55 -> 1 | F56: =F45+F55 -> 1 | G56: =G45+G55 -> 1 | H56: =H45+H55 -> 1

Sheet balance sheet
A1: HEROMOTOCORP LTD
A2: BALANCE SHEET
A3: INR ( CR )
A5: PARTICULAR | C5: 41729 | D5: 42094 | E5: 42460 | F5: 42825 | G5: 43190 | H5: 43555
A6: ASSETS
A7: NON - CURRENT ASSET
A8: property , plant and equipment | C8: 1897 | D8: 2851 | E8: 3907 | F8: 4495 | G8: 4771.4 | H8: 4792.5 | J8: Operating item
A9: capital work in progress | C9: 855 | D9: 315 | E9: 331 | F9: 386.5 | G9: 239 | H9: 384.9 | J9: Operating item
A10: intangible asset | C10: 350 | D10: 101 | E10: 129 | F10: 103.8 | G10: 189.6 | H10: 159.9 | J10: Operating item
A11: intangible asset under devolopment | C11: - | D11: 404 | E11: 323 | F11: 194.5 | G11: 116.5 | H11: 188 | J11: Operating item
A12: equity accounted investments in associates | C12: - | D12: 708 | E12: 950 | F12: 1025.4 | G12: 1159.6 | H12: 1705.9 | J12: non-operating item
A13: investments | C13: 878 | D13: 821 | E13: 945 | F13: 496.9 | G13: 918.5 | H13: 1234.1 | J13: non-operating item
A14: loans to employee | C14: 477 | D14: - | E14: - | F14: 23.1 | G14: 22.3 | H14: 60.1 | J14: non-operating item
A15: security deposits | C15: - | D15: - | E15: - | F15: 25.4 | G15: 23.6 | H15: 33.8 | J15: Operating item
A16: deferred tax assets ( net ) | C16: 106 | D16: 74 | E16: - | H16: - | J16: non-operating item
A17: income tax assets (net) | C17: - | D17: - | E17: - | F17: 332.5 | G17: 394.5 | H17: 855.6 | J17: Operating item
A18: other non-current assets | C18: - | D18: - | E18: - | F18: 658.4 | G18: 559.6 | H18: 676.5 | J18: Operating item
A19: TOTAL NON-CUURENT ASSET | C19: =SUM(C8:C18) -> 4563 | D19: =SUM(D8:D18) -> 5274 | E19: =SUM(E8:E18) -> 6585 | F19: =SUM(F8:F18) -> 7741.5 | G19: =SUM(G8:G18) -> 8394.6 | H19: =SUM(H8:H18) -> 10091.3
A21: CURRENT ASSET
A22: inventories | C22: 670 | D22: 861 | E22: 762 | F22: 708.6 | G22: 962.7 | H22: 1249.5 | J22: Operating item
A23: investments | C23: 3276 | D23: 2297 | E23: 3249 | F23: 4544.1 | G23: 5591.1 | H23: 3173.9 | J23: non - current item
A24: trade receivables | C24: 921 | D24: 1372 | E24: 1282 | F24: 1551.8 | G24: 1427 | H24: 2745.1 | J24: Operating item
A25: cash and cash equivalents | C25: 120 | D25: 216 | E25: 179 | F25: 74.1 | G25: 130.6 | H25: 208.1 | J25: Operating item
A26: bank balances | C26: - | D26: - | E26: - | F26: 121.3 | G26: 107 | H26: 95.8 | J26: Operating item
A27: loans to employees | C27: 18 | D27: 24 | E27: 24 | F27: 21.7 | G27: 21.4 | H27: 23.2 | J27: non - current item
A28: security deposits | C28: 1 | D28: - | E28: - | F28: 3.2 | G28: 7.1 | H28: 1.9 | J28: Operating item
A29: other financial asset | C29: 22 | D29: 60 | E29: 79 | F29: 145 | G29: 543.3 | H29: 654.2 | J29: Operating item
A30: other cuurent asset | C30: 531 | D30: 550 | E30: 512 | F30: 400.8 | G30: 212.1 | H30: 261.5 | J30: Operating item
A31: Total current asset | C31: =SUM(C22:C30) -> 5559 | D31: =SUM(D22:D30) -> 5380 | E31: =SUM(E22:E30) -> 6087 | F31: =SUM(F22:F30) -> 7570.6 | G31: =SUM(G22:G30) -> 9002.3 | H31: =SUM(H22:H30) -> 8413.2
A32: TOTAL ASSETS | C32: =C19+C31 -> 10122 | D32: =D19+D31 -> 10654 | E32: =E19+E31 -> 12672 | F32: =F19+F31 -> 15312.1 | G32: =G19+G31 -> 17396.9 | H32: =H19+H31 -> 18504.5
A34: PARTICULARS | C34: 41729 | D34: 42094 | E34: 42460 | F34: 42825 | G34: 43190 | H34: 43555
A35: LIABILITIES
A36: NON-CURRENT LIABILITIES
A37: Equity share capital | C37: 39.9 | D37: 39.9 | E37: 39.9 | F37: 39.9 | G37: 39.9 | H37: 40 | J37: non - current item
A38: other equity | C38: 5582.7 | D38: 6500.1 | E38: 7912.7 | F38: 10275.6 | G38: 11931.5 | H38: 13080.5 | J38: non - current item
A39: non-controlling interest | C39: 0.9 | D39: 18.5 | E39: 53.6 | F39: 67.4 | G39: 93.2 | H39: 116.1 | J39: non - current item
A40: LT debt | C40: - | D40: 12 | E40: 146 | F40: 207.9 | G40: 149.6 | H40: 124.8 | J40: non - current item
A41: employee benefits | C41: 8.7 | D41: 10.2 | E41: 15.7 | F41: 16.2 | G41: 25.9 | H41: 28.4 | J41: non - current item
A42: other long term liabilities | C42: 24.5 | D42: 31.3 | E42: 34.9 | F42: - | G42: - | H42: - | J42: Operating item
A43: warrenties | C43: 41.4 | D43: 56.1 | E43: 69 | F43: 59.5 | G43: 93.2 | H43: 92.5 | J43: Operating item
A44: deferred tax liabilities ( net ) | C44: - | D44: - | E44: 227.8 | F44: 468.9 | G44: 581.9 | H44: 612.9 | J44: non - current item
A45: Total non -cuurent liabilities | C45: =SUM(C37:C44) -> 5698.1 | D45: =SUM(D37:D44) -> 6668.1 | E45: =SUM(E37:E44) -> 8499.6 | F45: =SUM(F37:F44) -> 11135.4 | G45: =SUM(G37:G44) -> 12915.2 | H45: =SUM(H37:H44) -> 14095.2
A47: CURRENT LIABILITIES
A48: ST debt | C48: - | D48: 88 | E48: 84.1 | F48: 40.1 | G48: 75.4 | H48: 183.7 | J48: non - current item
A49: trade payables | C49: 2291 | D49: 2713.1 | E49: 2791.7 | F49: 3266.2 | G49: 3375.3 | H49: 3438.2 | J49: Operating item
A50: other financial liabilities | C50: 540.4 | D50: 399.1 | E50: 442.9 | F50: 308.7 | G50: 147.7 | H50: 167 | J50: non - current item
A51: security deposits dealers and others | C51: 47.8 | D51: 51.6 | E51: 54.6 | F51: 62.5 | G51: 57.7 | H51: 59.8 | J51: Operating item
A52: other curent liabilities | C52: 1534.2 | D52: 721.2 | E52: 769.1 | F52: 456.6 | G52: 765 | H52: 500.8 | J52: Operating item
A53: employee benefits | C53: 2.9 | D53: 2.9 | E53: 3.7 | F53: 5.1 | G53: 5.7 | H53: 5.8 | J53: non - current item
A54: warranties | C54: 7.6 | D54: 10.3 | E54: 26.3 | F54: 37.5 | G54: 54.9 | H54: 53.9 | J54: Operating item
A55: Total current liabilities | C55: =SUM(C49:C54) -> 4423.9 | D55: =SUM(D48:D54) -> 3986.2 | E55: =SUM(E48:E54) -> 4172.4 | F55: =SUM(F48:F54) -> 4176.7 | G55: =SUM(G48:G54) -> 4481.7 | H55: =SUM(H48:H54) -> 4409.2
A56: Total liabilities | C56: =C45+C55 -> 10122 | D56: =D45+D55 -> 10654.3 | E56: =E45+E55 -> 12672 | F56: =F45+F55 -> 15312.1 | G56: =G45+G55 -> 17396.9 | H56: =H45+H55 -> 18504.4

Sheet RATIO ANALYSIS
A1: 1 | B1: GROWTH | I1: NEGATIVE
B2: particular | C2: 41699 | D2: 42064 | E2: 42430 | F2: 42795 | G2: 43160 | H2: 43525
B4: Revenue from operations | C4: 27005 | D4: 29021 | E4: 30715 | F4: 30984 | G4: 33101 | H4: 33972
B5: excise duty on sale of goods | C5: -1880 | D5: -1718 | E5: -2258 | F5: -2373 | G5: -643 | H5: -1
B6: NET SALES | C6: =SUM(C4:C5) -> 25125 | D6: =SUM(D4:D5) -> 27303 | E6: =SUM(E4:E5) -> 28457 | F6: =SUM(F4:F5) -> 28611 | G6: =SUM(G4:G5) -> 32458 | H6: =SUM(H4:H5) -> 33971
B7: Sales growth % | D7: =D6/C6-1 -> 0.086686567 | E7: =E6/D6-1 -> 0.042266418 | F7: =F6/E6-1 -> 0.0054116738 | G7: =G6/F6-1 -> 0.13445877 | H7: =H6/G6-1 -> 0.046614086
A8: 2 | I8: POSITIVE
B9: LIQUIDITY
B10: CURRENT ASSET | C10: ='balance sheet'!C31 -> 5559 | D10: ='balance sheet'!D31 -> 5380 | E10: ='balance sheet'!E31 -> 6087 | F10: ='balance sheet'!F31 -> 7570.6 | G10: ='balance sheet'!G31 -> 9002.3 | H10: ='balance sheet'!H31 -> 8413.2
B11: CURRENT LIABILITIES | C11: ='balance sheet'!C55 -> 4423.9 | D11: ='balance sheet'!D55 -> 3986.2 | E11: ='balance sheet'!E55 -> 4172.4 | F11: ='balance sheet'!F55 -> 4176.7 | G11: ='balance sheet'!G55 -> 4481.7 | H11: ='balance sheet'!H55 -> 4409.2
B12: CURRENT RATIO | C12: =C10/C11 -> 1.2565836 | D12: =D10/D11 -> 1.3496563 | E12: =E10/E11 -> 1.4588726 | F12: =F10/F11 -> 1.8125793 | G12: =G10/G11 -> 2.0086797 | H12: =H10/H11 -> 1.9081012
A13: 3 | I13: POSITIVE
B14: PROFITABILITY
B15: EBITDA | C15: ='income statement'!C12 -> 3539 | D15: ='income statement'!D12 -> 3497 | E15: ='income statement'!E12 -> 4397 | F15: ='income statement'!F12 -> 4576 | G15: ='income statement'!G12 -> 5325 | H15: ='income statement'!H12 -> 5018
B16: EBITDA MARGIN | C16: =C15/C6 -> 0.14085572 | D16: =D15/D6 -> 0.12808116 | E16: =E15/E6 -> 0.15451383 | F16: =F15/F6 -> 0.15993849 | G16: =G15/G6 -> 0.16405817 | H16: =H15/H6 -> 0.14771423
A17: 4
B18: ROE | C18: ='income statement'!C22/('balance sheet'!C37+'balance sheet'!C38) -> 0.3738484 | D18: ='income statement'!D22/('balance sheet'!D37+'balance sheet'!D38) -> 0.3616208 | E18: ='income statement'!E22/('balance sheet'!E37+'balance sheet'!E38) -> 0.3916958 | F18: ='income statement'!F22/('balance sheet'!F37+'balance sheet'!F38) -> 0.34385149 | G18: ='income statement'!G22/('balance sheet'!G37+'balance sheet'!G38) -> 0.31090766 | H18: ='income statement'!H22/('balance sheet'!H37+'balance sheet'!H38) -> 0.26424298
B19: NET PROFIT / NET SALES | C19: ='income statement'!C22/'RATIO ANALYSIS'!C6 -> 0.083661692 | D19: ='income statement'!D22/'RATIO ANALYSIS'!D6 -> 0.086620518 | E19: ='income statement'!E22/'RATIO ANALYSIS'!E6 -> 0.1094634 | F19: ='income statement'!F22/'RATIO ANALYSIS'!F6 -> 0.1239733 | G19: ='income statement'!G22/'RATIO ANALYSIS'!G6 -> 0.11467127 | H19: ='income statement'!H22/'RATIO ANALYSIS'!H6 -> 0.10205764 | I19: CAPEX
B20: NET SALES / TOTAL ASSET | C20: =C6/'balance sheet'!C32 -> 2.482217 | D20: =D6/'balance sheet'!D32 -> 2.5626995 | E20: =E6/'balance sheet'!E32 -> 2.2456597 | F20: =F6/'balance sheet'!F32 -> 1.8685223 | G20: =G6/'balance sheet'!G32 -> 1.8657347 | H20: =H6/'balance sheet'!H32 -> 1.8358237
B21: TOTAL ASSET / SHAREHOLDER's EQUITY | C21: ='balance sheet'!C32/('balance sheet'!C37+'balance sheet'!C38) -> 1.8002348 | D21: ='balance sheet'!D32/('balance sheet'!D37+'balance sheet'!D38) -> 1.629052 | E21: ='balance sheet'!E32/('balance sheet'!E37+'balance sheet'!E38) -> 1.5934411 | F21: ='balance sheet'!F32/('balance sheet'!F37+'balance sheet'!F38) -> 1.4843779 | G21: ='balance sheet'!G32/('balance sheet'!G37+'balance sheet'!G38) -> 1.4532051 | H21: ='balance sheet'!H32/('balance sheet'!H37+'balance sheet'!H38) -> 1.4103502
B22: ROE | C22: =C19*C20*C21 -> 0.3738484 | D22: =D19*D20*D21 -> 0.3616208 | E22: =E19*E20*E21 -> 0.3916958 | F22: =F19*F20*F21 -> 0.34385149 | G22: =G19*G20*G21 -> 0.31090766 | H22: =H19*H20*H21 -> 0.26424298
A23: 5
B24: SOLVENCY | I24: POSITIVE
B25: DEBT/EQUITY | C25: 0 | D25: =('balance sheet'!D40+'balance sheet'!D48)/('balance sheet'!D37+'balance sheet'!D38) -> 0.01529052 | E25: =('balance sheet'!E40+'balance sheet'!E48)/('balance sheet'!E37+'balance sheet'!E38) -> 0.028933934 | F25: =('balance sheet'!F40+'balance sheet'!F48)/('balance sheet'!F37+'balance sheet'!F38) -> 0.024041491 | G25: =('balance sheet'!G40+'balance sheet'!G48)/('balance sheet'!G37+'balance sheet'!G38) -> 0.018794794 | H25: =('balance sheet'!H40+'balance sheet'!H48)/('balance sheet'!H37+'balance sheet'!H38) -> 0.023512823
B26: EBITDA/INTEREST EXPENSES | C26: =-C15/'income statement'!C16 -> 294.91667 | D26: =-D15/'income statement'!D16 -> 291.41667 | E26: =-E15/'income statement'!E16 -> 293.13333 | F26: =-F15/'income statement'!F16 -> 169.48148 | G26: =-G15/'income statement'!G16 -> 171.77419 | H26: =-H15/'income statement'!H16 -> 135.62162

Sheet CASHFLOW STATEMENT
A1: CASH FLOW STAEMENT
A2: INR ( CR )
A4: PARTICULAR | C4: 41729 | D4: 42094 | E4: 42460 | F4: 42825 | G4: 43190
A5: Net cash from operating activities | C5: 2963 | D5: 2186 | E5: 3796 | F5: 4007 | G5: 4017
A6: capex | C6: -937 | D6: -1230 | E6: -1701 | F6: -1237 | G6: -822
A7: Free cash flow | C7: =SUM(C5:C6) -> 2026 | D7: =SUM(D5:D6) -> 956 | E7: =SUM(E5:E6) -> 2095 | F7: =SUM(F5:F6) -> 2770 | G7: =SUM(G5:G6) -> 3195
